tcolorpy/__init__.py
tcolorpy/__main__.py
tcolorpy/__version__.py
tcolorpy/_const.py
tcolorpy/_truecolor.py
tcolorpy/py.typed
tcolorpy-0.1.6.dist-info/LICENSE
tcolorpy-0.1.6.dist-info/METADATA
tcolorpy-0.1.6.dist-info/WHEEL
tcolorpy-0.1.6.dist-info/top_level.txt
tcolorpy-0.1.6.dist-info/RECORD
