Metadata-Version: 2.1
Name: tcolorpy
Version: 0.1.6
Summary: tcolopy is a Python library to apply true color for terminal text.
Home-page: https://github.com/thombashi/tcolorpy
Author: Tsuyoshi Hombashi
Author-email: tsuyoshi.hombashi@gmail.com
License: MIT License
Project-URL: Changlog, https://github.com/thombashi/tcolorpy/blob/master/CHANGELOG.md
Project-URL: Source, https://github.com/thombashi/tcolorpy
Project-URL: Tracker, https://github.com/thombashi/tcolorpy/issues
Keywords: ANSI escape,terminal color,truecolor
Classifier: Development Status :: 4 - Beta
Classifier: Intended Audience :: Information Technology
Classifier: License :: OSI Approved :: MIT License
Classifier: Operating System :: OS Independent
Classifier: Programming Language :: Python :: 3
Classifier: Programming Language :: Python :: 3.7
Classifier: Programming Language :: Python :: 3.8
Classifier: Programming Language :: Python :: 3.9
Classifier: Programming Language :: Python :: 3.10
Classifier: Programming Language :: Python :: 3.11
Classifier: Programming Language :: Python :: 3.12
Classifier: Programming Language :: Python :: 3 :: Only
Classifier: Programming Language :: Python :: Implementation :: CPython
Classifier: Programming Language :: Python :: Implementation :: PyPy
Classifier: Topic :: Software Development :: Libraries
Classifier: Topic :: Software Development :: Libraries :: Python Modules
Classifier: Topic :: Terminals
Classifier: Topic :: Text Processing
Classifier: Typing :: Typed
Requires-Python: >=3.7
License-File: LICENSE
Provides-Extra: test
Requires-Dist: pytest>=6.0.1; extra == "test"
Requires-Dist: pytest-md-report>=0.5; extra == "test"
